{"nodes": [{"id": "lib_admin_store_AdminStore", "label": "Admin Store", "file_type": "code", "source_file": "lib/admin-store.ts", "source_location": null, "source_url": null, "captured_at": null, "author": null, "contributor": null}, {"id": "lib_admin_store_Category", "label": "Category", "file_type": "code", "source_file": "lib/admin-store.ts", "source_location": null, "source_url": null, "captured_at": null, "author": null, "contributor": null}, {"id": "lib_admin_store_DeliveryZone", "label": "Delivery Zone", "file_type": "code", "source_file": "lib/admin-store.ts", "source_location": null, "source_url": null, "captured_at": null, "author": null, "contributor": null}, {"id": "lib_admin_store_AdminUser", "label": "Admin User", "file_type": "code", "source_file": "lib/admin-store.ts", "source_location": null, "source_url": null, "captured_at": null, "author": null, "contributor": null}, {"id": "lib_admin_store_Order", "label": "Order", "file_type": "code", "source_file": "lib/admin-store.ts", "source_location": null, "source_url": null, "captured_at": null, "author": null, "contributor": null}, {"id": "lib_admin_store_OrderItem", "label": "Order Item", "file_type": "code", "source_file": "lib/admin-store.ts", "source_location": null, "source_url": null, "captured_at": null, "author": null, "contributor": null}, {"id": "lib_admin_store_Currency", "label": "Currency", "file_type": "code", "source_file": "lib/admin-store.ts", "source_location": null, "source_url": null, "captured_at": null, "author": null, "contributor": null}], "edges": [{"source": "lib_admin_store_AdminStore", "target": "lib_store_Product", "relation": "shares_data_with", "confidence": "EXTRACTED", "confidence_score": 1.0, "source_file": "lib/admin-store.ts", "source_location": null, "weight": 1.0}, {"source": "lib_admin_store_AdminStore", "target": "lib_admin_store_Category", "relation": "shares_data_with", "confidence": "EXTRACTED", "confidence_score": 1.0, "source_file": "lib/admin-store.ts", "source_location": null, "weight": 1.0}, {"source": "lib_admin_store_AdminStore", "target": "lib_admin_store_DeliveryZone", "relation": "shares_data_with", "confidence": "EXTRACTED", "confidence_score": 1.0, "source_file": "lib/admin-store.ts", "source_location": null, "weight": 1.0}, {"source": "lib_admin_store_AdminStore", "target": "lib_admin_store_AdminUser", "relation": "shares_data_with", "confidence": "EXTRACTED", "confidence_score": 1.0, "source_file": "lib/admin-store.ts", "source_location": null, "weight": 1.0}, {"source": "lib_admin_store_AdminStore", "target": "lib_admin_store_Order", "relation": "shares_data_with", "confidence": "EXTRACTED", "confidence_score": 1.0, "source_file": "lib/admin-store.ts", "source_location": null, "weight": 1.0}, {"source": "lib_admin_store_AdminStore", "target": "lib_admin_store_Currency", "relation": "shares_data_with", "confidence": "EXTRACTED", "confidence_score": 1.0, "source_file": "lib/admin-store.ts", "source_location": null, "weight": 1.0}, {"source": "lib_admin_store_AdminStore", "target": "lib_products_SeedProducts", "relation": "references", "confidence": "EXTRACTED", "confidence_score": 1.0, "source_file": "lib/admin-store.ts", "source_location": null, "weight": 1.0}, {"source": "lib_admin_store_Order", "target": "lib_admin_store_OrderItem", "relation": "shares_data_with", "confidence": "EXTRACTED", "confidence_score": 1.0, "source_file": "lib/admin-store.ts", "source_location": null, "weight": 1.0}, {"source": "lib_admin_store_OrderItem", "target": "lib_store_Product", "relation": "conceptually_related_to", "confidence": "INFERRED", "confidence_score": 0.9, "source_file": "lib/admin-store.ts", "source_location": null, "weight": 1.0}], "hyperedges": [{"id": "admin_crud_ecosystem", "label": "Admin CRUD Ecosystem", "nodes": ["lib_admin_store_AdminStore", "app_admin_page_AdminDashboard", "app_admin_productos_page_ProductsAdmin", "app_admin_productos_id_page_ProductDetailAdmin", "app_admin_categorias_page_CategoriesAdmin", "app_admin_usuarios_page_UsersPage", "app_admin_ordenes_page_OrdersPage", "app_admin_monedas_page_CurrenciesPage"], "relation": "participate_in", "confidence": "EXTRACTED", "confidence_score": 1.0, "source_file": "lib/admin-store.ts"}]}